signalfx/__init__.py
signalfx/aws.py
signalfx/constants.py
signalfx/ingest.py
signalfx/rest.py
signalfx/version.py
signalfx/generated_protocol_buffers/__init__.py
signalfx/generated_protocol_buffers/signal_fx_protocol_buffers_pb2.py
signalfx/pyformance/__init__.py
signalfx/pyformance/metadata.py
signalfx/pyformance/registry.py
signalfx/pyformance/reporter.py
signalfx/signalflow/__init__.py
signalfx/signalflow/channel.py
signalfx/signalflow/computation.py
signalfx/signalflow/errors.py
signalfx/signalflow/messages.py
signalfx/signalflow/sse.py
signalfx/signalflow/transport.py
signalfx/signalflow/ws.py
signalfx-1.1.15.dist-info/LICENSE
signalfx-1.1.15.dist-info/METADATA
signalfx-1.1.15.dist-info/WHEEL
signalfx-1.1.15.dist-info/top_level.txt
signalfx-1.1.15.dist-info/zip-safe
signalfx-1.1.15.dist-info/RECORD
