Metadata-Version: 2.1
Name: signalfx
Version: 1.1.15
Summary: SignalFx Python Library
Home-page: https://github.com/signalfx/signalfx-python
Author: SignalFx, Inc
Author-email: info@signalfx.com
License: Apache Software License v2
Platform: UNKNOWN
Classifier: Operating System :: OS Independent
Classifier: Programming Language :: Python
Classifier: Programming Language :: Python :: 2
Classifier: Programming Language :: Python :: 2.7
Classifier: Programming Language :: Python :: 3
Classifier: Programming Language :: Python :: 3.5
Classifier: Programming Language :: Python :: 3.6
Classifier: Programming Language :: Python :: 3.7
Classifier: Programming Language :: Python :: 3.8
License-File: LICENSE
Requires-Dist: certifi
Requires-Dist: protobuf (==3.20.1)
Requires-Dist: pyformance (>=0.3.1)
Requires-Dist: requests (>=2.7.0)
Requires-Dist: sseclient-py (>=1.4)
Requires-Dist: urllib3 (>=1.15.1)
Requires-Dist: six (>=1.6.0)
Requires-Dist: ws4py (>=0.4.1)
